{
	"results": {
		"aflpp": {
			"sqlite3": {
				"sqlite3_fuzz": {
					"4": {
						"reached": {
							"SQL016": 270,
							"SQL013": 58320,
							"SQL002": 180,
							"SQL010": 240,
							"SQL017": 240,
							"SQL015": 180,
							"SQL018": 1350,
							"SQL011": 40440,
							"SQL006": 61500,
							"SQL012": 16620,
							"SQL007": 120,
							"SQL019": 570,
							"SQL014": 1320,
							"SQL009": 900
						},
						"triggered": {
							"SQL002": 900,
							"SQL018": 1350,
							"SQL014": 2640
						}
					},
					"3": {
						"reached": {
							"SQL016": 270,
							"SQL002": 210,
							"SQL010": 270,
							"SQL017": 270,
							"SQL015": 210,
							"SQL018": 1620,
							"SQL006": 13530,
							"SQL012": 51030,
							"SQL007": 180,
							"SQL019": 510,
							"SQL014": 420,
							"SQL009": 900
						},
						"triggered": {
							"SQL002": 3720,
							"SQL018": 1770,
							"SQL012": 63270,
							"SQL014": 22710
						}
					},
					"2": {
						"reached": {
							"SQL016": 210,
							"SQL002": 120,
							"SQL015": 150,
							"SQL010": 240,
							"SQL017": 240,
							"SQL018": 270,
							"SQL012": 31590,
							"SQL007": 150,
							"SQL019": 210,
							"SQL014": 2460,
							"SQL009": 450
						},
						"triggered": {
							"SQL002": 1380,
							"SQL018": 24150,
							"SQL014": 20760
						}
					},
					"1": {
						"reached": {
							"SQL016": 270,
							"SQL002": 120,
							"SQL010": 270,
							"SQL017": 270,
							"SQL015": 240,
							"SQL018": 360,
							"SQL007": 240,
							"SQL019": 300,
							"SQL014": 390,
							"SQL009": 720
						},
						"triggered": {
							"SQL002": 390,
							"SQL018": 960,
							"SQL014": 960
						}
					},
					"0": {
						"reached": {
							"SQL016": 240,
							"SQL002": 120,
							"SQL010": 240,
							"SQL017": 240,
							"SQL015": 120,
							"SQL018": 330,
							"SQL006": 48750,
							"SQL003": 49680,
							"SQL012": 61230,
							"SQL007": 90,
							"SQL019": 330,
							"SQL014": 7980,
							"SQL009": 390
						},
						"triggered": {
							"SQL002": 3150,
							"SQL018": 21210,
							"SQL014": 20340
						}
					}
				}
			},
			"php": {
				"exif": {
					"4": {
						"reached": {
							"PHP011": 60,
							"PHP003": 90,
							"PHP004": 90,
							"PHP009": 90,
							"PHP002": 90
						},
						"triggered": {
							"PHP011": 90,
							"PHP009": 7830
						}
					},
					"3": {
						"reached": {
							"PHP011": 60,
							"PHP003": 90,
							"PHP004": 90,
							"PHP009": 90,
							"PHP002": 90
						},
						"triggered": {
							"PHP011": 330,
							"PHP009": 630
						}
					},
					"2": {
						"reached": {
							"PHP011": 60,
							"PHP003": 90,
							"PHP004": 90,
							"PHP009": 90,
							"PHP002": 90
						},
						"triggered": {
							"PHP011": 90,
							"PHP004": 30660,
							"PHP009": 150
						}
					},
					"1": {
						"reached": {
							"PHP011": 60,
							"PHP003": 90,
							"PHP004": 90,
							"PHP009": 90,
							"PHP002": 90
						},
						"triggered": {
							"PHP011": 270,
							"PHP004": 1200,
							"PHP009": 840
						}
					},
					"0": {
						"reached": {
							"PHP011": 60,
							"PHP003": 90,
							"PHP004": 90,
							"PHP009": 90,
							"PHP002": 90
						},
						"triggered": {
							"PHP011": 270,
							"PHP009": 28170
						}
					}
				}
			},
			"openssl": {
				"x509": {
					"4": {
						"reached": {
							"SSL003": 60,
							"SSL009": 90,
							"SSL001": 90,
							"SSL016": 90,
							"SSL010": 90
						},
						"triggered": {}
					},
					"3": {
						"reached": {
							"SSL003": 60,
							"SSL009": 90,
							"SSL001": 90,
							"SSL016": 90,
							"SSL010": 90
						},
						"triggered": {}
					},
					"2": {
						"reached": {
							"SSL003": 60,
							"SSL009": 90,
							"SSL001": 90,
							"SSL016": 90,
							"SSL010": 90
						},
						"triggered": {}
					},
					"1": {
						"reached": {
							"SSL003": 60,
							"SSL009": 90,
							"SSL001": 90,
							"SSL016": 90,
							"SSL010": 90
						},
						"triggered": {}
					},
					"0": {
						"reached": {
							"SSL003": 60,
							"SSL009": 90,
							"SSL001": 90,
							"SSL016": 90,
							"SSL010": 90
						},
						"triggered": {}
					}
				},
				"client": {
					"4": {
						"reached": {
							"SSL003": 90,
							"SSL002": 90,
							"SSL001": 90,
							"SSL016": 120,
							"SSL008": 90,
							"SSL019": 60,
							"SSL010": 90
						},
						"triggered": {
							"SSL002": 540
						}
					},
					"3": {
						"reached": {
							"SSL003": 90,
							"SSL002": 90,
							"SSL001": 90,
							"SSL016": 120,
							"SSL008": 90,
							"SSL019": 60,
							"SSL010": 90
						},
						"triggered": {
							"SSL002": 570
						}
					},
					"2": {
						"reached": {
							"SSL003": 90,
							"SSL002": 90,
							"SSL001": 90,
							"SSL016": 120,
							"SSL008": 90,
							"SSL019": 60,
							"SSL010": 90
						},
						"triggered": {
							"SSL002": 570
						}
					},
					"1": {
						"reached": {
							"SSL003": 90,
							"SSL002": 90,
							"SSL001": 90,
							"SSL016": 120,
							"SSL008": 90,
							"SSL019": 60,
							"SSL010": 90
						},
						"triggered": {
							"SSL002": 540
						}
					},
					"0": {
						"reached": {
							"SSL003": 90,
							"SSL002": 90,
							"SSL001": 90,
							"SSL016": 120,
							"SSL008": 90,
							"SSL019": 60,
							"SSL010": 90
						},
						"triggered": {
							"SSL002": 600
						}
					}
				},
				"server": {
					"4": {
						"reached": {
							"SSL003": 60,
							"SSL002": 90,
							"SSL005": 90,
							"SSL020": 90,
							"SSL019": 90,
							"SSL010": 90
						},
						"triggered": {
							"SSL002": 840,
							"SSL020": 39090
						}
					},
					"3": {
						"reached": {
							"SSL003": 60,
							"SSL002": 90,
							"SSL005": 90,
							"SSL020": 90,
							"SSL019": 90,
							"SSL010": 90
						},
						"triggered": {
							"SSL002": 810
						}
					},
					"2": {
						"reached": {
							"SSL003": 60,
							"SSL002": 90,
							"SSL005": 90,
							"SSL020": 90,
							"SSL019": 90,
							"SSL010": 90
						},
						"triggered": {
							"SSL002": 840
						}
					},
					"1": {
						"reached": {
							"SSL003": 60,
							"SSL002": 90,
							"SSL005": 90,
							"SSL020": 90,
							"SSL019": 90,
							"SSL010": 90
						},
						"triggered": {
							"SSL002": 840
						}
					},
					"0": {
						"reached": {
							"SSL003": 60,
							"SSL002": 90,
							"SSL005": 90,
							"SSL020": 90,
							"SSL019": 90,
							"SSL010": 90
						},
						"triggered": {
							"SSL002": 810
						}
					}
				},
				"bignum": {
					"4": {
						"reached": {
							"SSL010": 60
						},
						"triggered": {}
					},
					"3": {
						"reached": {
							"SSL010": 60
						},
						"triggered": {}
					},
					"2": {
						"reached": {
							"SSL010": 60
						},
						"triggered": {}
					},
					"1": {
						"reached": {
							"SSL010": 60
						},
						"triggered": {}
					},
					"0": {
						"reached": {
							"SSL010": 60
						},
						"triggered": {}
					}
				},
				"asn1parse": {
					"4": {
						"reached": {
							"SSL010": 60
						},
						"triggered": {}
					},
					"3": {
						"reached": {
							"SSL010": 60
						},
						"triggered": {}
					},
					"2": {
						"reached": {
							"SSL010": 60
						},
						"triggered": {}
					},
					"1": {
						"reached": {
							"SSL010": 60
						},
						"triggered": {}
					},
					"0": {
						"reached": {
							"SSL010": 60
						},
						"triggered": {}
					}
				},
				"asn1": {
					"4": {
						"reached": {
							"SSL010": 60,
							"SSL016": 90,
							"SSL003": 90,
							"SSL001": 90
						},
						"triggered": {
							"SSL003": 420,
							"SSL001": 2730
						}
					},
					"3": {
						"reached": {
							"SSL010": 60,
							"SSL016": 90,
							"SSL003": 90,
							"SSL001": 90
						},
						"triggered": {
							"SSL003": 420,
							"SSL001": 26700
						}
					},
					"2": {
						"reached": {
							"SSL010": 60,
							"SSL016": 90,
							"SSL003": 90,
							"SSL001": 90
						},
						"triggered": {
							"SSL003": 420,
							"SSL001": 3300
						}
					},
					"1": {
						"reached": {
							"SSL010": 60,
							"SSL016": 90,
							"SSL003": 90,
							"SSL001": 90
						},
						"triggered": {
							"SSL003": 420,
							"SSL001": 6090
						}
					},
					"0": {
						"reached": {
							"SSL010": 60,
							"SSL016": 90,
							"SSL003": 90,
							"SSL001": 90
						},
						"triggered": {
							"SSL003": 420,
							"SSL001": 48960
						}
					}
				}
			},
			"lua": {
				"lua": {
					"4": {
						"reached": {
							"LUA004": 51450,
							"LUA002": 51480
						},
						"triggered": {
							"LUA004": 51480
						}
					},
					"3": {
						"reached": {
							"LUA004": 60,
							"LUA002": 360
						},
						"triggered": {
							"LUA004": 360
						}
					},
					"2": {
						"reached": {
							"LUA004": 60,
							"LUA002": 180,
							"LUA001": 180
						},
						"triggered": {
							"LUA004": 20400,
							"LUA002": 22740
						}
					},
					"1": {
						"reached": {
							"LUA004": 60,
							"LUA002": 240,
							"LUA001": 240
						},
						"triggered": {
							"LUA004": 20580
						}
					},
					"0": {
						"reached": {
							"LUA004": 60,
							"LUA002": 330,
							"LUA001": 86130
						},
						"triggered": {
							"LUA004": 330
						}
					}
				}
			},
			"libxml2": {
				"xmllint": {
					"4": {
						"reached": {
							"XML017": 60,
							"XML009": 90,
							"XML001": 90,
							"XML008": 150,
							"XML003": 90,
							"XML012": 90,
							"XML006": 90
						},
						"triggered": {
							"XML017": 90,
							"XML009": 8970
						}
					},
					"3": {
						"reached": {
							"XML017": 60,
							"XML009": 90,
							"XML001": 90,
							"XML008": 120,
							"XML003": 90,
							"XML012": 90,
							"XML006": 90
						},
						"triggered": {
							"XML017": 90,
							"XML009": 2880
						}
					},
					"2": {
						"reached": {
							"XML017": 60,
							"XML009": 90,
							"XML001": 90,
							"XML008": 150,
							"XML003": 90,
							"XML012": 90,
							"XML006": 90
						},
						"triggered": {
							"XML017": 90,
							"XML009": 6060,
							"XML001": 31770
						}
					},
					"1": {
						"reached": {
							"XML017": 60,
							"XML009": 90,
							"XML001": 90,
							"XML008": 180,
							"XML003": 90,
							"XML012": 90,
							"XML006": 90
						},
						"triggered": {
							"XML017": 90,
							"XML009": 3420,
							"XML001": 29790
						}
					},
					"0": {
						"reached": {
							"XML017": 60,
							"XML009": 90,
							"XML001": 90,
							"XML008": 210,
							"XML003": 90,
							"XML012": 90,
							"XML006": 90
						},
						"triggered": {
							"XML017": 90,
							"XML009": 7380,
							"XML001": 67650
						}
					}
				},
				"libxml2_xml_read_memory_fuzzer": {
					"4": {
						"reached": {
							"XML017": 60,
							"XML009": 90,
							"XML011": 90,
							"XML001": 90,
							"XML008": 90,
							"XML003": 90,
							"XML012": 90,
							"XML006": 90
						},
						"triggered": {
							"XML017": 90,
							"XML009": 5640,
							"XML001": 2640,
							"XML003": 10500
						}
					},
					"3": {
						"reached": {
							"XML017": 60,
							"XML009": 90,
							"XML011": 90,
							"XML001": 90,
							"XML008": 90,
							"XML003": 90,
							"XML012": 90,
							"XML006": 90
						},
						"triggered": {
							"XML017": 90,
							"XML009": 3690,
							"XML001": 1920,
							"XML003": 6630
						}
					},
					"2": {
						"reached": {
							"XML017": 60,
							"XML009": 90,
							"XML011": 90,
							"XML001": 90,
							"XML002": 32790,
							"XML008": 90,
							"XML003": 90,
							"XML012": 90,
							"XML006": 90
						},
						"triggered": {
							"XML017": 90,
							"XML009": 17070,
							"XML001": 4530,
							"XML002": 32790,
							"XML003": 1890
						}
					},
					"1": {
						"reached": {
							"XML017": 60,
							"XML009": 90,
							"XML011": 90,
							"XML001": 90,
							"XML008": 90,
							"XML003": 90,
							"XML012": 90,
							"XML006": 90
						},
						"triggered": {
							"XML017": 90,
							"XML009": 6210,
							"XML001": 3840,
							"XML003": 3180,
							"XML012": 70110
						}
					},
					"0": {
						"reached": {
							"XML017": 60,
							"XML009": 90,
							"XML011": 90,
							"XML001": 90,
							"XML008": 90,
							"XML003": 90,
							"XML012": 90,
							"XML006": 90
						},
						"triggered": {
							"XML017": 90,
							"XML009": 5460,
							"XML001": 4470,
							"XML003": 540
						}
					}
				}
			},
			"libtiff": {
				"tiffcp": {
					"4": {
						"reached": {
							"TIF006": 1980,
							"TIF014": 90,
							"TIF007": 90,
							"TIF003": 60,
							"TIF009": 12690,
							"TIF012": 30,
							"TIF005": 1980,
							"TIF010": 2370
						},
						"triggered": {
							"TIF006": 1980,
							"TIF014": 5370,
							"TIF007": 90,
							"TIF009": 12690,
							"TIF012": 1650,
							"TIF005": 1980
						}
					},
					"3": {
						"reached": {
							"TIF006": 1590,
							"TIF014": 120,
							"TIF007": 120,
							"TIF003": 60,
							"TIF012": 30,
							"TIF005": 1560,
							"TIF010": 3390
						},
						"triggered": {
							"TIF006": 1590,
							"TIF014": 900,
							"TIF007": 270,
							"TIF012": 1830,
							"TIF005": 1560
						}
					},
					"2": {
						"reached": {
							"TIF006": 2460,
							"TIF014": 90,
							"TIF007": 90,
							"TIF003": 60,
							"TIF009": 14790,
							"TIF002": 57690,
							"TIF012": 30,
							"TIF005": 2460,
							"TIF010": 8280
						},
						"triggered": {
							"TIF006": 2460,
							"TIF014": 2100,
							"TIF007": 180,
							"TIF009": 14790,
							"TIF012": 4500,
							"TIF005": 2460
						}
					},
					"1": {
						"reached": {
							"TIF006": 2070,
							"TIF014": 90,
							"TIF007": 90,
							"TIF003": 60,
							"TIF009": 4680,
							"TIF012": 30,
							"TIF005": 3240,
							"TIF010": 3900
						},
						"triggered": {
							"TIF006": 2070,
							"TIF014": 6180,
							"TIF007": 180,
							"TIF009": 6090,
							"TIF012": 1620,
							"TIF005": 3240
						}
					},
					"0": {
						"reached": {
							"TIF006": 7560,
							"TIF014": 90,
							"TIF007": 90,
							"TIF003": 60,
							"TIF012": 30,
							"TIF005": 9360,
							"TIF010": 5070
						},
						"triggered": {
							"TIF006": 7560,
							"TIF014": 3120,
							"TIF007": 150,
							"TIF012": 3720,
							"TIF005": 9360
						}
					}
				},
				"tiff_read_rgba_fuzzer": {
					"4": {
						"reached": {
							"TIF014": 120,
							"TIF007": 120,
							"TIF003": 90,
							"TIF002": 43950,
							"TIF012": 60,
							"TIF001": 75060,
							"TIF010": 9210
						},
						"triggered": {
							"TIF014": 3000,
							"TIF007": 300,
							"TIF012": 1620
						}
					},
					"3": {
						"reached": {
							"TIF014": 120,
							"TIF007": 120,
							"TIF003": 90,
							"TIF002": 35550,
							"TIF012": 60,
							"TIF010": 3480
						},
						"triggered": {
							"TIF014": 2220,
							"TIF007": 330,
							"TIF002": 36240,
							"TIF012": 3390
						}
					},
					"2": {
						"reached": {
							"TIF014": 450,
							"TIF007": 450,
							"TIF003": 90,
							"TIF002": 36720,
							"TIF012": 60,
							"TIF010": 10620
						},
						"triggered": {
							"TIF014": 3240,
							"TIF007": 600,
							"TIF002": 36720,
							"TIF012": 540
						}
					},
					"1": {
						"reached": {
							"TIF014": 480,
							"TIF007": 480,
							"TIF003": 90,
							"TIF002": 13230,
							"TIF012": 60,
							"TIF010": 5460
						},
						"triggered": {
							"TIF014": 4140,
							"TIF007": 690,
							"TIF012": 810
						}
					},
					"0": {
						"reached": {
							"TIF014": 180,
							"TIF007": 180,
							"TIF003": 90,
							"TIF002": 7020,
							"TIF008": 13410,
							"TIF012": 60,
							"TIF010": 5970
						},
						"triggered": {
							"TIF014": 4290,
							"TIF007": 660,
							"TIF002": 37770,
							"TIF008": 13680,
							"TIF012": 3810
						}
					}
				}
			},
			"libpng": {
				"libpng_read_fuzzer": {
					"4": {
						"reached": {
							"PNG006": 90,
							"PNG001": 90,
							"PNG003": 60,
							"PNG005": 90,
							"PNG004": 90,
							"PNG007": 90
						},
						"triggered": {
							"PNG006": 150,
							"PNG003": 90,
							"PNG007": 25590
						}
					},
					"3": {
						"reached": {
							"PNG006": 90,
							"PNG001": 90,
							"PNG003": 60,
							"PNG005": 90,
							"PNG004": 90,
							"PNG007": 90
						},
						"triggered": {
							"PNG006": 360,
							"PNG003": 90
						}
					},
					"2": {
						"reached": {
							"PNG006": 90,
							"PNG001": 90,
							"PNG003": 60,
							"PNG005": 90,
							"PNG004": 90,
							"PNG007": 90
						},
						"triggered": {
							"PNG006": 390,
							"PNG003": 120
						}
					},
					"1": {
						"reached": {
							"PNG006": 90,
							"PNG001": 90,
							"PNG003": 60,
							"PNG005": 90,
							"PNG004": 90,
							"PNG007": 90
						},
						"triggered": {
							"PNG006": 180,
							"PNG003": 90,
							"PNG007": 4050
						}
					},
					"0": {
						"reached": {
							"PNG006": 90,
							"PNG001": 90,
							"PNG003": 60,
							"PNG005": 90,
							"PNG004": 90,
							"PNG007": 90
						},
						"triggered": {
							"PNG006": 180,
							"PNG003": 90,
							"PNG007": 8190
						}
					}
				}
			}
		},
		"acecov": {
			"sqlite3": {
				"sqlite3_fuzz": {
					"4": {
						"reached": {
							"SQL016": 150,
							"SQL013": 49260,
							"SQL002": 90,
							"SQL010": 150,
							"SQL017": 150,
							"SQL015": 150,
							"SQL018": 3000,
							"SQL020": 50220,
							"SQL012": 53130,
							"SQL007": 150,
							"SQL019": 360,
							"SQL014": 840,
							"SQL009": 1200
						},
						"triggered": {
							"SQL013": 49260,
							"SQL002": 390,
							"SQL018": 14220,
							"SQL020": 50220,
							"SQL014": 6900
						}
					},
					"3": {
						"reached": {
							"SQL016": 180,
							"SQL013": 57780,
							"SQL002": 120,
							"SQL015": 120,
							"SQL010": 210,
							"SQL017": 210,
							"SQL018": 540,
							"SQL006": 45180,
							"SQL012": 72510,
							"SQL007": 90,
							"SQL019": 180,
							"SQL014": 420,
							"SQL009": 510
						},
						"triggered": {
							"SQL002": 210,
							"SQL018": 870,
							"SQL014": 5730
						}
					},
					"2": {
						"reached": {
							"SQL016": 210,
							"SQL002": 120,
							"SQL010": 210,
							"SQL015": 150,
							"SQL017": 210,
							"SQL018": 210,
							"SQL020": 53250,
							"SQL012": 34350,
							"SQL007": 150,
							"SQL019": 180,
							"SQL014": 1320,
							"SQL009": 2190
						},
						"triggered": {
							"SQL002": 1320,
							"SQL018": 4800,
							"SQL020": 53250,
							"SQL014": 5340
						}
					},
					"1": {
						"reached": {
							"SQL016": 150,
							"SQL013": 54630,
							"SQL002": 120,
							"SQL010": 150,
							"SQL017": 150,
							"SQL015": 120,
							"SQL018": 240,
							"SQL011": 29310,
							"SQL020": 59430,
							"SQL006": 79620,
							"SQL012": 15570,
							"SQL007": 90,
							"SQL019": 690,
							"SQL014": 1050,
							"SQL009": 930
						},
						"triggered": {
							"SQL002": 1530,
							"SQL018": 7320,
							"SQL020": 59430,
							"SQL014": 20460
						}
					},
					"0": {
						"reached": {
							"SQL016": 360,
							"SQL018": 360,
							"SQL002": 120,
							"SQL015": 150,
							"SQL010": 360,
							"SQL017": 360,
							"SQL020": 14820,
							"SQL006": 68010,
							"SQL011": 73320,
							"SQL012": 47100,
							"SQL007": 150,
							"SQL019": 270,
							"SQL014": 8610,
							"SQL009": 1440
						},
						"triggered": {
							"SQL018": 27210,
							"SQL002": 840,
							"SQL020": 14820,
							"SQL014": 27270
						}
					}
				}
			},
			"php": {
				"exif": {
					"4": {
						"reached": {
							"PHP011": 60,
							"PHP003": 90,
							"PHP004": 90,
							"PHP009": 90,
							"PHP002": 90
						},
						"triggered": {
							"PHP011": 150,
							"PHP009": 1560
						}
					},
					"3": {
						"reached": {
							"PHP011": 60,
							"PHP003": 90,
							"PHP004": 90,
							"PHP009": 90,
							"PHP002": 90
						},
						"triggered": {
							"PHP011": 210,
							"PHP009": 8880
						}
					},
					"2": {
						"reached": {
							"PHP011": 60,
							"PHP003": 90,
							"PHP004": 90,
							"PHP009": 90,
							"PHP002": 90
						},
						"triggered": {
							"PHP011": 150,
							"PHP009": 2610
						}
					},
					"1": {
						"reached": {
							"PHP011": 60,
							"PHP003": 90,
							"PHP004": 90,
							"PHP009": 90,
							"PHP002": 90
						},
						"triggered": {
							"PHP011": 120,
							"PHP009": 64050
						}
					},
					"0": {
						"reached": {
							"PHP011": 60,
							"PHP003": 90,
							"PHP004": 90,
							"PHP009": 90,
							"PHP002": 90
						},
						"triggered": {
							"PHP011": 180,
							"PHP009": 8040
						}
					}
				}
			},
			"openssl": {
				"x509": {
					"4": {
						"reached": {
							"SSL003": 60,
							"SSL009": 90,
							"SSL001": 90,
							"SSL016": 90,
							"SSL010": 90
						},
						"triggered": {}
					},
					"3": {
						"reached": {
							"SSL003": 60,
							"SSL009": 90,
							"SSL001": 90,
							"SSL016": 90,
							"SSL010": 90
						},
						"triggered": {}
					},
					"2": {
						"reached": {
							"SSL003": 60,
							"SSL009": 90,
							"SSL001": 90,
							"SSL016": 90,
							"SSL010": 90
						},
						"triggered": {}
					},
					"1": {
						"reached": {
							"SSL003": 60,
							"SSL009": 90,
							"SSL001": 90,
							"SSL016": 90,
							"SSL010": 90
						},
						"triggered": {}
					},
					"0": {
						"reached": {
							"SSL003": 60,
							"SSL009": 90,
							"SSL001": 90,
							"SSL016": 90,
							"SSL010": 90
						},
						"triggered": {}
					}
				},
				"client": {
					"4": {
						"reached": {
							"SSL003": 90,
							"SSL002": 90,
							"SSL001": 90,
							"SSL016": 120,
							"SSL008": 90,
							"SSL019": 60,
							"SSL010": 90
						},
						"triggered": {
							"SSL002": 570
						}
					},
					"3": {
						"reached": {
							"SSL003": 90,
							"SSL002": 90,
							"SSL001": 90,
							"SSL016": 120,
							"SSL008": 90,
							"SSL019": 60,
							"SSL010": 90
						},
						"triggered": {
							"SSL002": 570
						}
					},
					"2": {
						"reached": {
							"SSL003": 90,
							"SSL002": 90,
							"SSL001": 90,
							"SSL016": 120,
							"SSL008": 90,
							"SSL019": 60,
							"SSL010": 90
						},
						"triggered": {
							"SSL002": 570
						}
					},
					"1": {
						"reached": {
							"SSL003": 90,
							"SSL002": 90,
							"SSL001": 90,
							"SSL016": 120,
							"SSL008": 90,
							"SSL019": 60,
							"SSL010": 90
						},
						"triggered": {
							"SSL002": 570
						}
					},
					"0": {
						"reached": {
							"SSL003": 90,
							"SSL002": 90,
							"SSL001": 90,
							"SSL016": 120,
							"SSL008": 90,
							"SSL019": 60,
							"SSL010": 90
						},
						"triggered": {
							"SSL002": 600
						}
					}
				},
				"server": {
					"4": {
						"reached": {
							"SSL003": 60,
							"SSL002": 90,
							"SSL005": 90,
							"SSL020": 90,
							"SSL019": 90,
							"SSL010": 90
						},
						"triggered": {
							"SSL002": 840
						}
					},
					"3": {
						"reached": {
							"SSL003": 60,
							"SSL002": 90,
							"SSL005": 90,
							"SSL020": 90,
							"SSL019": 90,
							"SSL010": 90
						},
						"triggered": {
							"SSL002": 870
						}
					},
					"2": {
						"reached": {
							"SSL003": 60,
							"SSL002": 90,
							"SSL005": 90,
							"SSL020": 90,
							"SSL019": 90,
							"SSL010": 90
						},
						"triggered": {
							"SSL002": 840
						}
					},
					"1": {
						"reached": {
							"SSL003": 60,
							"SSL002": 90,
							"SSL005": 90,
							"SSL020": 90,
							"SSL019": 90,
							"SSL010": 90
						},
						"triggered": {
							"SSL002": 840
						}
					},
					"0": {
						"reached": {
							"SSL003": 60,
							"SSL002": 90,
							"SSL005": 90,
							"SSL020": 90,
							"SSL019": 90,
							"SSL010": 90
						},
						"triggered": {
							"SSL002": 900
						}
					}
				},
				"bignum": {
					"4": {
						"reached": {
							"SSL010": 60
						},
						"triggered": {}
					},
					"3": {
						"reached": {
							"SSL010": 60
						},
						"triggered": {}
					},
					"2": {
						"reached": {
							"SSL010": 60
						},
						"triggered": {}
					},
					"1": {
						"reached": {
							"SSL010": 60
						},
						"triggered": {}
					},
					"0": {
						"reached": {
							"SSL010": 60
						},
						"triggered": {}
					}
				},
				"asn1parse": {
					"4": {
						"reached": {
							"SSL010": 60
						},
						"triggered": {}
					},
					"3": {
						"reached": {
							"SSL010": 60
						},
						"triggered": {}
					},
					"2": {
						"reached": {
							"SSL010": 60
						},
						"triggered": {}
					},
					"1": {
						"reached": {
							"SSL010": 60
						},
						"triggered": {}
					},
					"0": {
						"reached": {
							"SSL010": 60
						},
						"triggered": {}
					}
				},
				"asn1": {
					"4": {
						"reached": {
							"SSL010": 60,
							"SSL016": 90,
							"SSL003": 90,
							"SSL001": 90
						},
						"triggered": {
							"SSL003": 420,
							"SSL001": 43110
						}
					},
					"3": {
						"reached": {
							"SSL010": 60,
							"SSL016": 90,
							"SSL003": 90,
							"SSL001": 90
						},
						"triggered": {
							"SSL003": 420,
							"SSL001": 26160
						}
					},
					"2": {
						"reached": {
							"SSL010": 60,
							"SSL016": 90,
							"SSL003": 90,
							"SSL001": 90
						},
						"triggered": {
							"SSL003": 420,
							"SSL001": 1950
						}
					},
					"1": {
						"reached": {
							"SSL010": 60,
							"SSL016": 90,
							"SSL003": 90,
							"SSL001": 90
						},
						"triggered": {
							"SSL003": 420,
							"SSL001": 13350
						}
					},
					"0": {
						"reached": {
							"SSL010": 60,
							"SSL016": 90,
							"SSL003": 90,
							"SSL001": 90
						},
						"triggered": {
							"SSL003": 450,
							"SSL001": 71940
						}
					}
				}
			},
			"lua": {
				"lua": {
					"4": {
						"reached": {
							"LUA004": 9360,
							"LUA002": 29700
						},
						"triggered": {
							"LUA002": 82860
						}
					},
					"3": {
						"reached": {
							"LUA004": 63420,
							"LUA002": 63450
						},
						"triggered": {
							"LUA002": 64920
						}
					},
					"2": {
						"reached": {
							"LUA004": 60,
							"LUA002": 360
						},
						"triggered": {
							"LUA004": 360
						}
					},
					"1": {
						"reached": {
							"LUA004": 60,
							"LUA002": 360,
							"LUA001": 360
						},
						"triggered": {
							"LUA004": 45600,
							"LUA002": 72450
						}
					},
					"0": {
						"reached": {
							"LUA004": 60,
							"LUA002": 360,
							"LUA001": 360
						},
						"triggered": {
							"LUA004": 44250,
							"LUA002": 65220
						}
					}
				}
			},
			"libxml2": {
				"xmllint": {
					"4": {
						"reached": {
							"XML017": 60,
							"XML009": 90,
							"XML001": 90,
							"XML008": 180,
							"XML003": 90,
							"XML012": 90,
							"XML006": 90
						},
						"triggered": {
							"XML017": 90,
							"XML009": 4170
						}
					},
					"3": {
						"reached": {
							"XML017": 60,
							"XML009": 90,
							"XML001": 90,
							"XML008": 120,
							"XML003": 90,
							"XML012": 90,
							"XML006": 90
						},
						"triggered": {
							"XML017": 90,
							"XML009": 1950
						}
					},
					"2": {
						"reached": {
							"XML017": 60,
							"XML009": 90,
							"XML001": 90,
							"XML008": 150,
							"XML003": 90,
							"XML012": 90,
							"XML006": 90
						},
						"triggered": {
							"XML017": 90,
							"XML009": 8310
						}
					},
					"1": {
						"reached": {
							"XML017": 60,
							"XML009": 90,
							"XML001": 90,
							"XML008": 120,
							"XML003": 90,
							"XML012": 90,
							"XML006": 90
						},
						"triggered": {
							"XML017": 90,
							"XML009": 1860,
							"XML001": 27510
						}
					},
					"0": {
						"reached": {
							"XML017": 60,
							"XML009": 90,
							"XML001": 90,
							"XML002": 27450,
							"XML008": 150,
							"XML003": 90,
							"XML012": 90,
							"XML006": 90
						},
						"triggered": {
							"XML017": 90,
							"XML009": 5370,
							"XML001": 27120,
							"XML002": 27450
						}
					}
				},
				"libxml2_xml_read_memory_fuzzer": {
					"4": {
						"reached": {
							"XML017": 60,
							"XML009": 90,
							"XML011": 90,
							"XML001": 90,
							"XML008": 90,
							"XML003": 90,
							"XML012": 90,
							"XML006": 90
						},
						"triggered": {
							"XML017": 150,
							"XML009": 23640,
							"XML001": 1200,
							"XML003": 12390
						}
					},
					"3": {
						"reached": {
							"XML017": 60,
							"XML009": 90,
							"XML011": 90,
							"XML001": 90,
							"XML002": 210,
							"XML008": 90,
							"XML003": 90,
							"XML012": 90,
							"XML006": 90
						},
						"triggered": {
							"XML017": 120,
							"XML009": 6180,
							"XML001": 5010,
							"XML002": 210,
							"XML003": 4590
						}
					},
					"2": {
						"reached": {
							"XML017": 60,
							"XML009": 90,
							"XML011": 90,
							"XML001": 90,
							"XML008": 90,
							"XML003": 90,
							"XML012": 90,
							"XML006": 90
						},
						"triggered": {
							"XML017": 90,
							"XML009": 2220,
							"XML001": 5910,
							"XML003": 5220
						}
					},
					"1": {
						"reached": {
							"XML017": 60,
							"XML009": 90,
							"XML011": 90,
							"XML001": 90,
							"XML008": 90,
							"XML003": 90,
							"XML012": 90,
							"XML006": 90
						},
						"triggered": {
							"XML017": 120,
							"XML009": 2370,
							"XML001": 4080,
							"XML003": 11010
						}
					},
					"0": {
						"reached": {
							"XML017": 60,
							"XML009": 90,
							"XML011": 90,
							"XML001": 90,
							"XML008": 90,
							"XML003": 90,
							"XML012": 90,
							"XML006": 90
						},
						"triggered": {
							"XML017": 150,
							"XML009": 2310,
							"XML001": 1170,
							"XML003": 7860
						}
					}
				}
			},
			"libtiff": {
				"tiffcp": {
					"4": {
						"reached": {
							"TIF006": 540,
							"TIF014": 60,
							"TIF007": 60,
							"TIF003": 60,
							"TIF002": 19470,
							"TIF008": 47700,
							"TIF012": 30,
							"TIF005": 540,
							"TIF010": 2100
						},
						"triggered": {
							"TIF006": 540,
							"TIF014": 480,
							"TIF007": 480,
							"TIF002": 21360,
							"TIF008": 48180,
							"TIF012": 3930,
							"TIF005": 540
						}
					},
					"3": {
						"reached": {
							"TIF006": 90,
							"TIF014": 60,
							"TIF007": 60,
							"TIF003": 60,
							"TIF009": 23580,
							"TIF012": 30,
							"TIF005": 90,
							"TIF010": 2730
						},
						"triggered": {
							"TIF006": 90,
							"TIF014": 4170,
							"TIF007": 90,
							"TIF009": 23580,
							"TIF012": 1200,
							"TIF005": 90
						}
					},
					"2": {
						"reached": {
							"TIF006": 120,
							"TIF014": 60,
							"TIF007": 60,
							"TIF003": 60,
							"TIF009": 20610,
							"TIF012": 30,
							"TIF005": 120,
							"TIF010": 2100
						},
						"triggered": {
							"TIF006": 120,
							"TIF014": 240,
							"TIF007": 270,
							"TIF009": 30240,
							"TIF012": 840,
							"TIF005": 120
						}
					},
					"1": {
						"reached": {
							"TIF006": 330,
							"TIF014": 60,
							"TIF007": 60,
							"TIF003": 60,
							"TIF012": 30,
							"TIF001": 16950,
							"TIF005": 330,
							"TIF010": 6030
						},
						"triggered": {
							"TIF006": 330,
							"TIF014": 1290,
							"TIF007": 90,
							"TIF012": 3030,
							"TIF005": 330
						}
					},
					"0": {
						"reached": {
							"TIF006": 16290,
							"TIF014": 60,
							"TIF007": 60,
							"TIF003": 60,
							"TIF009": 6960,
							"TIF012": 30,
							"TIF005": 3060,
							"TIF010": 2880
						},
						"triggered": {
							"TIF006": 16290,
							"TIF014": 2640,
							"TIF007": 120,
							"TIF009": 6960,
							"TIF012": 4260,
							"TIF005": 3060
						}
					}
				},
				"tiff_read_rgba_fuzzer": {
					"4": {
						"reached": {
							"TIF014": 90,
							"TIF007": 90,
							"TIF003": 90,
							"TIF002": 29610,
							"TIF012": 60,
							"TIF010": 3510
						},
						"triggered": {
							"TIF014": 930,
							"TIF007": 90,
							"TIF002": 54930,
							"TIF012": 1320
						}
					},
					"3": {
						"reached": {
							"TIF014": 90,
							"TIF007": 90,
							"TIF003": 90,
							"TIF002": 47220,
							"TIF008": 34260,
							"TIF012": 60,
							"TIF010": 4320
						},
						"triggered": {
							"TIF014": 270,
							"TIF007": 240,
							"TIF002": 47220,
							"TIF008": 53760,
							"TIF012": 720
						}
					},
					"2": {
						"reached": {
							"TIF014": 90,
							"TIF007": 90,
							"TIF003": 90,
							"TIF002": 46020,
							"TIF012": 60,
							"TIF010": 4860
						},
						"triggered": {
							"TIF014": 960,
							"TIF007": 150,
							"TIF012": 2760
						}
					},
					"1": {
						"reached": {
							"TIF014": 90,
							"TIF007": 90,
							"TIF003": 90,
							"TIF002": 43350,
							"TIF012": 60,
							"TIF010": 4110
						},
						"triggered": {
							"TIF014": 3480,
							"TIF007": 210,
							"TIF002": 43350,
							"TIF012": 2430
						}
					},
					"0": {
						"reached": {
							"TIF014": 90,
							"TIF007": 90,
							"TIF003": 90,
							"TIF002": 13860,
							"TIF008": 49290,
							"TIF012": 60,
							"TIF010": 4290
						},
						"triggered": {
							"TIF014": 3030,
							"TIF007": 330,
							"TIF002": 25080,
							"TIF008": 67950,
							"TIF012": 270
						}
					}
				}
			},
			"libpng": {
				"libpng_read_fuzzer": {
					"4": {
						"reached": {
							"PNG006": 90,
							"PNG001": 90,
							"PNG003": 60,
							"PNG005": 90,
							"PNG004": 90,
							"PNG007": 90
						},
						"triggered": {
							"PNG006": 240,
							"PNG003": 90,
							"PNG007": 15300
						}
					},
					"3": {
						"reached": {
							"PNG006": 90,
							"PNG001": 90,
							"PNG003": 60,
							"PNG005": 90,
							"PNG004": 90,
							"PNG007": 90
						},
						"triggered": {
							"PNG006": 120,
							"PNG003": 90,
							"PNG007": 8250
						}
					},
					"2": {
						"reached": {
							"PNG006": 90,
							"PNG001": 90,
							"PNG003": 60,
							"PNG005": 90,
							"PNG004": 90,
							"PNG007": 90
						},
						"triggered": {
							"PNG006": 210,
							"PNG003": 90,
							"PNG007": 23910
						}
					},
					"1": {
						"reached": {
							"PNG006": 90,
							"PNG001": 90,
							"PNG003": 60,
							"PNG005": 90,
							"PNG004": 90,
							"PNG007": 90
						},
						"triggered": {
							"PNG006": 300,
							"PNG003": 90,
							"PNG007": 12630
						}
					},
					"0": {
						"reached": {
							"PNG006": 90,
							"PNG001": 90,
							"PNG003": 60,
							"PNG005": 90,
							"PNG004": 90,
							"PNG007": 90
						},
						"triggered": {
							"PNG006": 210,
							"PNG003": 120
						}
					}
				}
			}
		},
		"ddfuzz": {
			"sqlite3": {
				"sqlite3_fuzz": {
					"4": {
						"reached": {
							"SQL002": 150,
							"SQL010": 1800,
							"SQL015": 150,
							"SQL019": 960,
							"SQL007": 120,
							"SQL016": 1800,
							"SQL014": 7620,
							"SQL017": 1800,
							"SQL018": 4650,
							"SQL009": 7230
						},
						"triggered": {
							"SQL002": 7710,
							"SQL014": 20190,
							"SQL018": 32130
						}
					},
					"3": {
						"reached": {
							"SQL002": 720,
							"SQL010": 750,
							"SQL015": 720,
							"SQL007": 690,
							"SQL016": 750,
							"SQL019": 3120,
							"SQL014": 6210,
							"SQL017": 750,
							"SQL018": 2100,
							"SQL009": 4080
						},
						"triggered": {
							"SQL002": 4650
						}
					},
					"2": {
						"reached": {
							"SQL016": 2040,
							"SQL002": 330,
							"SQL015": 330,
							"SQL019": 1830,
							"SQL007": 150,
							"SQL010": 2100,
							"SQL014": 16200,
							"SQL017": 2130,
							"SQL018": 5250,
							"SQL009": 6780,
							"SQL020": 80280
						},
						"triggered": {
							"SQL002": 17490,
							"SQL014": 21300,
							"SQL018": 52680,
							"SQL020": 80280
						}
					},
					"1": {
						"reached": {
							"SQL002": 150,
							"SQL010": 1890,
							"SQL015": 150,
							"SQL019": 1800,
							"SQL007": 90,
							"SQL016": 1890,
							"SQL014": 38850,
							"SQL017": 1890,
							"SQL018": 9840,
							"SQL009": 27390,
							"SQL020": 65400
						},
						"triggered": {
							"SQL002": 20910,
							"SQL014": 46020,
							"SQL018": 11820,
							"SQL020": 65400
						}
					},
					"0": {
						"reached": {
							"SQL002": 150,
							"SQL010": 150,
							"SQL015": 150,
							"SQL007": 90,
							"SQL016": 210,
							"SQL019": 3150,
							"SQL014": 8790,
							"SQL017": 150,
							"SQL018": 3720,
							"SQL013": 38430,
							"SQL009": 12000
						},
						"triggered": {
							"SQL002": 9480,
							"SQL014": 18960,
							"SQL018": 21570
						}
					}
				}
			},
			"php": {
				"exif": {
					"4": {
						"reached": {
							"PHP011": 60,
							"PHP002": 90,
							"PHP003": 90,
							"PHP009": 90,
							"PHP004": 90
						},
						"triggered": {
							"PHP011": 1110,
							"PHP009": 1710
						}
					},
					"3": {
						"reached": {
							"PHP011": 60,
							"PHP002": 180,
							"PHP003": 180,
							"PHP009": 180,
							"PHP004": 180
						},
						"triggered": {
							"PHP011": 840,
							"PHP009": 39060
						}
					},
					"2": {
						"reached": {
							"PHP011": 60,
							"PHP002": 90,
							"PHP003": 90,
							"PHP009": 90,
							"PHP004": 90
						},
						"triggered": {
							"PHP011": 660,
							"PHP009": 4410
						}
					},
					"1": {
						"reached": {
							"PHP011": 60,
							"PHP002": 270,
							"PHP003": 270,
							"PHP009": 270,
							"PHP004": 270
						},
						"triggered": {
							"PHP011": 660,
							"PHP009": 5190,
							"PHP004": 2760
						}
					},
					"0": {
						"reached": {
							"PHP011": 60,
							"PHP002": 90,
							"PHP003": 90,
							"PHP009": 90,
							"PHP004": 90
						},
						"triggered": {
							"PHP011": 1110,
							"PHP009": 1260,
							"PHP004": 4590
						}
					}
				}
			},
			"openssl": {
				"x509": {
					"4": {
						"reached": {
							"SSL003": 60,
							"SSL010": 90,
							"SSL001": 90,
							"SSL009": 90,
							"SSL016": 90
						},
						"triggered": {}
					},
					"3": {
						"reached": {
							"SSL003": 60,
							"SSL010": 90,
							"SSL001": 90,
							"SSL009": 90,
							"SSL016": 90
						},
						"triggered": {}
					},
					"2": {
						"reached": {
							"SSL003": 60,
							"SSL010": 90,
							"SSL001": 90,
							"SSL009": 90,
							"SSL016": 90
						},
						"triggered": {}
					},
					"1": {
						"reached": {
							"SSL003": 60,
							"SSL010": 90,
							"SSL001": 90,
							"SSL009": 90,
							"SSL016": 90
						},
						"triggered": {}
					},
					"0": {
						"reached": {
							"SSL003": 60,
							"SSL010": 90,
							"SSL001": 90,
							"SSL009": 90,
							"SSL016": 90
						},
						"triggered": {}
					}
				},
				"client": {
					"4": {
						"reached": {
							"SSL003": 90,
							"SSL010": 90,
							"SSL001": 90,
							"SSL019": 60,
							"SSL002": 90,
							"SSL008": 90,
							"SSL016": 120
						},
						"triggered": {
							"SSL002": 690
						}
					},
					"3": {
						"reached": {
							"SSL003": 90,
							"SSL010": 90,
							"SSL001": 90,
							"SSL019": 60,
							"SSL002": 90,
							"SSL008": 90,
							"SSL016": 120
						},
						"triggered": {
							"SSL002": 630
						}
					},
					"2": {
						"reached": {
							"SSL003": 90,
							"SSL010": 90,
							"SSL001": 90,
							"SSL019": 60,
							"SSL002": 90,
							"SSL008": 90,
							"SSL016": 120
						},
						"triggered": {
							"SSL002": 630
						}
					},
					"1": {
						"reached": {
							"SSL003": 90,
							"SSL010": 90,
							"SSL001": 90,
							"SSL019": 60,
							"SSL002": 90,
							"SSL008": 90,
							"SSL016": 120
						},
						"triggered": {
							"SSL002": 630
						}
					},
					"0": {
						"reached": {
							"SSL003": 90,
							"SSL010": 90,
							"SSL001": 90,
							"SSL019": 60,
							"SSL002": 90,
							"SSL008": 90,
							"SSL016": 120
						},
						"triggered": {
							"SSL002": 630
						}
					}
				},
				"server": {
					"4": {
						"reached": {
							"SSL020": 90,
							"SSL003": 60,
							"SSL010": 90,
							"SSL019": 90,
							"SSL002": 90,
							"SSL005": 90
						},
						"triggered": {
							"SSL002": 960
						}
					},
					"3": {
						"reached": {
							"SSL020": 90,
							"SSL003": 60,
							"SSL010": 90,
							"SSL019": 90,
							"SSL002": 90,
							"SSL005": 90
						},
						"triggered": {
							"SSL002": 1020
						}
					},
					"2": {
						"reached": {
							"SSL020": 90,
							"SSL003": 60,
							"SSL010": 90,
							"SSL019": 90,
							"SSL002": 90,
							"SSL005": 90
						},
						"triggered": {
							"SSL002": 990
						}
					},
					"1": {
						"reached": {
							"SSL020": 90,
							"SSL003": 60,
							"SSL010": 90,
							"SSL019": 90,
							"SSL002": 90,
							"SSL005": 90
						},
						"triggered": {
							"SSL002": 960
						}
					},
					"0": {
						"reached": {
							"SSL020": 90,
							"SSL003": 60,
							"SSL010": 90,
							"SSL019": 90,
							"SSL002": 90,
							"SSL005": 90
						},
						"triggered": {
							"SSL002": 990
						}
					}
				},
				"bignum": {
					"4": {
						"reached": {
							"SSL010": 60
						},
						"triggered": {}
					},
					"3": {
						"reached": {
							"SSL010": 60
						},
						"triggered": {}
					},
					"2": {
						"reached": {
							"SSL010": 60
						},
						"triggered": {}
					},
					"1": {
						"reached": {
							"SSL010": 60
						},
						"triggered": {}
					},
					"0": {
						"reached": {
							"SSL010": 60
						},
						"triggered": {}
					}
				},
				"asn1parse": {
					"4": {
						"reached": {
							"SSL010": 60
						},
						"triggered": {}
					},
					"3": {
						"reached": {
							"SSL010": 60
						},
						"triggered": {}
					},
					"2": {
						"reached": {
							"SSL010": 60
						},
						"triggered": {}
					},
					"1": {
						"reached": {
							"SSL010": 60
						},
						"triggered": {}
					},
					"0": {
						"reached": {
							"SSL010": 60
						},
						"triggered": {}
					}
				},
				"asn1": {
					"4": {
						"reached": {
							"SSL016": 90,
							"SSL003": 90,
							"SSL010": 60,
							"SSL001": 90
						},
						"triggered": {
							"SSL003": 480,
							"SSL001": 13050
						}
					},
					"3": {
						"reached": {
							"SSL016": 90,
							"SSL003": 90,
							"SSL010": 60,
							"SSL001": 90
						},
						"triggered": {
							"SSL003": 480
						}
					},
					"2": {
						"reached": {
							"SSL016": 90,
							"SSL003": 90,
							"SSL010": 60,
							"SSL001": 90
						},
						"triggered": {
							"SSL003": 480,
							"SSL001": 9300
						}
					},
					"1": {
						"reached": {
							"SSL016": 90,
							"SSL003": 90,
							"SSL010": 60,
							"SSL001": 90
						},
						"triggered": {
							"SSL003": 480,
							"SSL001": 85200
						}
					},
					"0": {
						"reached": {
							"SSL016": 90,
							"SSL003": 90,
							"SSL010": 60,
							"SSL001": 90
						},
						"triggered": {
							"SSL003": 480,
							"SSL001": 14010
						}
					}
				}
			},
			"libxml2": {
				"xmllint": {
					"4": {
						"reached": {
							"XML009": 90,
							"XML008": 240,
							"XML001": 90,
							"XML012": 90,
							"XML003": 90,
							"XML006": 90,
							"XML017": 60
						},
						"triggered": {
							"XML009": 4830,
							"XML017": 150
						}
					},
					"3": {
						"reached": {
							"XML009": 90,
							"XML008": 150,
							"XML001": 90,
							"XML012": 90,
							"XML003": 90,
							"XML006": 90,
							"XML017": 60
						},
						"triggered": {
							"XML009": 13980,
							"XML017": 90
						}
					},
					"2": {
						"reached": {
							"XML011": 64950,
							"XML009": 90,
							"XML008": 240,
							"XML001": 90,
							"XML012": 90,
							"XML003": 90,
							"XML006": 90,
							"XML017": 60
						},
						"triggered": {
							"XML009": 3750,
							"XML017": 240
						}
					},
					"1": {
						"reached": {
							"XML009": 90,
							"XML008": 150,
							"XML001": 90,
							"XML012": 90,
							"XML003": 90,
							"XML006": 90,
							"XML017": 60
						},
						"triggered": {
							"XML009": 10950,
							"XML017": 90
						}
					},
					"0": {
						"reached": {
							"XML009": 90,
							"XML008": 240,
							"XML001": 90,
							"XML012": 90,
							"XML003": 90,
							"XML006": 90,
							"XML017": 60
						},
						"triggered": {
							"XML009": 1230,
							"XML017": 90
						}
					}
				},
				"libxml2_xml_read_memory_fuzzer": {
					"4": {
						"reached": {
							"XML011": 90,
							"XML009": 90,
							"XML008": 90,
							"XML001": 90,
							"XML012": 90,
							"XML003": 90,
							"XML006": 90,
							"XML017": 60
						},
						"triggered": {
							"XML009": 6900,
							"XML001": 12450,
							"XML003": 1830,
							"XML017": 270
						}
					},
					"3": {
						"reached": {
							"XML011": 90,
							"XML009": 90,
							"XML008": 90,
							"XML001": 90,
							"XML012": 90,
							"XML003": 90,
							"XML006": 90,
							"XML017": 60
						},
						"triggered": {
							"XML009": 1350,
							"XML001": 14430,
							"XML017": 90
						}
					},
					"2": {
						"reached": {
							"XML011": 90,
							"XML009": 90,
							"XML008": 90,
							"XML001": 90,
							"XML012": 90,
							"XML003": 90,
							"XML006": 90,
							"XML017": 60
						},
						"triggered": {
							"XML009": 79740,
							"XML001": 29520,
							"XML003": 11070,
							"XML017": 150
						}
					},
					"1": {
						"reached": {
							"XML011": 90,
							"XML009": 90,
							"XML008": 90,
							"XML001": 90,
							"XML012": 90,
							"XML003": 90,
							"XML006": 90,
							"XML017": 60
						},
						"triggered": {
							"XML009": 9210,
							"XML001": 37170,
							"XML017": 270
						}
					},
					"0": {
						"reached": {
							"XML011": 90,
							"XML009": 90,
							"XML008": 90,
							"XML001": 90,
							"XML012": 90,
							"XML003": 90,
							"XML006": 90,
							"XML017": 60
						},
						"triggered": {
							"XML009": 24210,
							"XML001": 12930,
							"XML017": 330
						}
					}
				}
			},
			"libtiff": {
				"tiffcp": {
					"4": {
						"reached": {
							"TIF003": 60,
							"TIF007": 60,
							"TIF006": 51090,
							"TIF012": 30,
							"TIF014": 60,
							"TIF010": 10590
						},
						"triggered": {
							"TIF007": 60,
							"TIF006": 51090,
							"TIF012": 1560,
							"TIF014": 3030
						}
					},
					"3": {
						"reached": {
							"TIF003": 60,
							"TIF007": 60,
							"TIF006": 3750,
							"TIF012": 30,
							"TIF014": 60,
							"TIF010": 7710
						},
						"triggered": {
							"TIF007": 150,
							"TIF006": 3750,
							"TIF012": 25740,
							"TIF014": 31140
						}
					},
					"2": {
						"reached": {
							"TIF003": 60,
							"TIF007": 60,
							"TIF006": 61260,
							"TIF012": 30,
							"TIF014": 60,
							"TIF010": 16890
						},
						"triggered": {
							"TIF007": 60,
							"TIF006": 61260,
							"TIF012": 2160,
							"TIF014": 28080
						}
					},
					"1": {
						"reached": {
							"TIF003": 60,
							"TIF007": 60,
							"TIF006": 44880,
							"TIF012": 30,
							"TIF014": 60,
							"TIF010": 3750
						},
						"triggered": {
							"TIF007": 60,
							"TIF006": 44880,
							"TIF012": 3330,
							"TIF014": 2280
						}
					},
					"0": {
						"reached": {
							"TIF003": 60,
							"TIF007": 60,
							"TIF006": 50250,
							"TIF012": 30,
							"TIF014": 60,
							"TIF010": 21390
						},
						"triggered": {
							"TIF007": 120,
							"TIF006": 50250,
							"TIF012": 6780,
							"TIF014": 7440
						}
					}
				},
				"tiff_read_rgba_fuzzer": {
					"4": {
						"reached": {
							"TIF003": 90,
							"TIF007": 90,
							"TIF012": 60,
							"TIF014": 90,
							"TIF010": 840
						},
						"triggered": {
							"TIF007": 120,
							"TIF012": 930,
							"TIF014": 6180
						}
					},
					"3": {
						"reached": {
							"TIF003": 90,
							"TIF007": 90,
							"TIF012": 60,
							"TIF014": 90,
							"TIF010": 1890
						},
						"triggered": {
							"TIF007": 120,
							"TIF012": 780,
							"TIF014": 26940
						}
					},
					"2": {
						"reached": {
							"TIF003": 90,
							"TIF007": 90,
							"TIF012": 60,
							"TIF014": 90,
							"TIF010": 11670
						},
						"triggered": {
							"TIF007": 120,
							"TIF012": 2040,
							"TIF014": 15990
						}
					},
					"1": {
						"reached": {
							"TIF003": 90,
							"TIF007": 90,
							"TIF012": 60,
							"TIF014": 90,
							"TIF010": 7230
						},
						"triggered": {
							"TIF007": 150,
							"TIF012": 450,
							"TIF014": 1680
						}
					},
					"0": {
						"reached": {
							"TIF003": 90,
							"TIF007": 90,
							"TIF012": 60,
							"TIF014": 90,
							"TIF010": 12630
						},
						"triggered": {
							"TIF007": 150,
							"TIF012": 600,
							"TIF014": 28470
						}
					}
				}
			},
			"libpng": {
				"libpng_read_fuzzer": {
					"4": {
						"reached": {
							"PNG005": 90,
							"PNG001": 90,
							"PNG004": 90,
							"PNG007": 90,
							"PNG003": 60,
							"PNG006": 90
						},
						"triggered": {
							"PNG003": 90
						}
					},
					"3": {
						"reached": {
							"PNG005": 90,
							"PNG001": 90,
							"PNG004": 90,
							"PNG007": 90,
							"PNG003": 60,
							"PNG006": 90
						},
						"triggered": {
							"PNG003": 90
						}
					},
					"2": {
						"reached": {
							"PNG005": 90,
							"PNG001": 90,
							"PNG004": 90,
							"PNG007": 90,
							"PNG003": 60,
							"PNG006": 90
						},
						"triggered": {
							"PNG007": 3300,
							"PNG003": 90
						}
					},
					"1": {
						"reached": {
							"PNG005": 90,
							"PNG001": 90,
							"PNG004": 120,
							"PNG007": 90,
							"PNG003": 60,
							"PNG006": 90
						},
						"triggered": {
							"PNG007": 5220,
							"PNG003": 90
						}
					},
					"0": {
						"reached": {
							"PNG005": 90,
							"PNG001": 90,
							"PNG004": 150,
							"PNG007": 90,
							"PNG003": 60,
							"PNG006": 90
						},
						"triggered": {
							"PNG003": 90
						}
					}
				}
			}
		}
	}
}